sgmcmcjax/__init__.py
sgmcmcjax/diffusion_util.py
sgmcmcjax/diffusions.py
sgmcmcjax/gradient_estimation.py
sgmcmcjax/kernels.py
sgmcmcjax/ksd.py
sgmcmcjax/optimizer.py
sgmcmcjax/samplers.py
sgmcmcjax/types.py
sgmcmcjax/util.py
sgmcmcjax/examples/__init__.py
sgmcmcjax/examples/gauss_optimize.py
sgmcmcjax/examples/gauss_sample_sgld.py
sgmcmcjax/examples/sgmcmc_nuts_demo.py
sgmcmcjax/examples/sgmcmc_utils.py
sgmcmcjax/models/__init__.py
sgmcmcjax/models/logistic_regression.py
sgmcmcjax/models/bayesian_NN/NN_data.py
sgmcmcjax/models/bayesian_NN/NN_model.py
sgmcmcjax/models/bayesian_NN/__init__.py
SGMCMCJax-0.2.13.dist-info/LICENSE
SGMCMCJax-0.2.13.dist-info/METADATA
SGMCMCJax-0.2.13.dist-info/WHEEL
SGMCMCJax-0.2.13.dist-info/top_level.txt
SGMCMCJax-0.2.13.dist-info/RECORD
