Metadata-Version: 2.1
Name: SGMCMCJax
Version: 0.2.13
Summary: SGMCMC samplers in JAX
Home-page: https://github.com/jeremiecoullon/SGMCMCJax
Author: Jeremie Coullon
Author-email: jeremie.coullon@gmail.com
License: LICENSE.txt
Platform: UNKNOWN
Requires-Dist: jax
Requires-Dist: jaxlib
Requires-Dist: tqdm
Requires-Dist: optax
Provides-Extra: docs
Requires-Dist: furo ==2020.12.30b24 ; extra == 'docs'
Requires-Dist: nbsphinx ==0.8.1 ; extra == 'docs'
Requires-Dist: nb-black ==1.0.7 ; extra == 'docs'
Requires-Dist: matplotlib ==3.3.3 ; extra == 'docs'
Requires-Dist: sphinx-copybutton ==0.3.5 ; extra == 'docs'
Requires-Dist: Sphinx ==4.4.0 ; extra == 'docs'
Requires-Dist: isort ==5.10.1 ; extra == 'docs'
Requires-Dist: sphinx-rtd-theme ==1.0.0 ; extra == 'docs'
Provides-Extra: tests
Requires-Dist: pytest ; extra == 'tests'
